bitcoin_graph/__init__.py
bitcoin_graph/__main__.py
bitcoin_graph/bitcoin_graph.py
test/__init__.py
test/test_bitcoin_graph.py
bitcoin_graph-0.1a1.dist-info/LICENSE
bitcoin_graph-0.1a1.dist-info/METADATA
bitcoin_graph-0.1a1.dist-info/WHEEL
bitcoin_graph-0.1a1.dist-info/top_level.txt
bitcoin_graph-0.1a1.dist-info/RECORD
