Metadata-Version: 2.1
Name: bitcoin-graph
Version: 0.1a1
Summary: A Python library for making matrices and graphs of Bitcoin wallet transactions
Home-page: https://github.com/joeblankenship1/bitcoin_graph
Author: Joe Blankenship
Author-email: info@cgrii.org
License: GPL-3.0
Platform: UNKNOWN
Classifier: License :: OSI Approved :: GNU Lesser General Public License v3 (LGPLv3)
Classifier: Programming Language :: Python :: 3
Classifier: Programming Language :: Python :: 3.7
Requires-Dist: blockchain (==1.4.4)
Requires-Dist: networkx (==2.3)
